school_api/__init__.py
school_api/config.py
school_api/exceptions.py
school_api/utils.py
school_api/check_code/__init__.py
school_api/check_code/predict.py
school_api/check_code/theta.dat
school_api/client/__init__.py
school_api/client/base.py
school_api/client/login_management.py
school_api/client/utils.py
school_api/client/api/__init__.py
school_api/client/api/base.py
school_api/client/api/login.py
school_api/client/api/place_schedule.py
school_api/client/api/schedule.py
school_api/client/api/score.py
school_api/client/api/user_info.py
school_api/client/api/utils/__init__.py
school_api/client/api/utils/schedule_parse.py
school_api/session/__init__.py
school_api/session/memorystorage.py
school_api/session/redisstorage.py
School_Api-1.5.0.dist-info/LICENSE
School_Api-1.5.0.dist-info/METADATA
School_Api-1.5.0.dist-info/WHEEL
School_Api-1.5.0.dist-info/top_level.txt
School_Api-1.5.0.dist-info/RECORD
