Metadata-Version: 2.1
Name: School-Api
Version: 1.5.0
Summary: School SDK for Python
Home-page: https://github.com/dairoot/school-api
Author: dairoot
Author-email: 623815825@qq.com
License: MIT
Platform: any
Classifier: Environment :: Web Environment
Classifier: Intended Audience :: Developers
Classifier: License :: OSI Approved :: MIT License
Classifier: Operating System :: OS Independent
Classifier: Programming Language :: Python :: 2.7
Classifier: Programming Language :: Python :: 3
Classifier: Programming Language :: Python :: 3.3
Classifier: Programming Language :: Python :: 3.4
Classifier: Programming Language :: Python :: 3.5
Classifier: Programming Language :: Python :: 3.6
Classifier: Programming Language :: Python :: 3.7
Classifier: Topic :: Internet :: WWW/HTTP :: Dynamic Content
Classifier: Topic :: Software Development :: Libraries :: Python Modules
Requires-Dist: six
Requires-Dist: requests
Requires-Dist: redis
Requires-Dist: bs4
Requires-Dist: pillow
Requires-Dist: numpy
